mutex.py
pg_mutex-1.0.2.dist-info/METADATA
pg_mutex-1.0.2.dist-info/WHEEL
pg_mutex-1.0.2.dist-info/top_level.txt
pg_mutex-1.0.2.dist-info/RECORD
