Metadata-Version: 2.1
Name: pg-mutex
Version: 1.0.2
Summary: UNKNOWN
Home-page: https://github.com/freeman1981/pg-mutex
License: UNKNOWN
Platform: UNKNOWN
Requires-Python: >=3.7
Requires-Dist: psycopg2-binary
